{
  "openapi": "3.0.1",
  "info": {
    "title": "Life Partner API",
    "version": "v1"
  },
  "paths": {
    "/api/Accounts": {
      "post": {
        "tags": [
          "Accounts"
        ],
        "requestBody": {
          "content": {
            "application/json": {
              "schema": {
                "$ref": "#/components/schemas/Accounts"
              }
            },
            "text/json": {
              "schema": {
                "$ref": "#/components/schemas/Accounts"
              }
            },
            "application/*+json": {
              "schema": {
                "$ref": "#/components/schemas/Accounts"
              }
            }
          }
        },
        "responses": {
          "200": {
            "description": "Success"
          }
        }
      },
      "get": {
        "tags": [
          "Accounts"
        ],
        "responses": {
          "200": {
            "description": "Success"
          }
        }
      },
      "put": {
        "tags": [
          "Accounts"
        ],
        "requestBody": {
          "content": {
            "application/json": {
              "schema": {
                "$ref": "#/components/schemas/Accounts"
              }
            },
            "text/json": {
              "schema": {
                "$ref": "#/components/schemas/Accounts"
              }
            },
            "application/*+json": {
              "schema": {
                "$ref": "#/components/schemas/Accounts"
              }
            }
          }
        },
        "responses": {
          "200": {
            "description": "Success"
          }
        }
      }
    },
    "/api/Accounts/{id}": {
      "get": {
        "tags": [
          "Accounts"
        ],
        "parameters": [
          {
            "name": "id",
            "in": "path",
            "required": true,
            "schema": {
              "type": "integer",
              "format": "int32"
            }
          }
        ],
        "responses": {
          "200": {
            "description": "Success"
          }
        }
      },
      "delete": {
        "tags": [
          "Accounts"
        ],
        "parameters": [
          {
            "name": "id",
            "in": "path",
            "required": true,
            "schema": {
              "type": "integer",
              "format": "int32"
            }
          }
        ],
        "responses": {
          "200": {
            "description": "Success"
          }
        }
      }
    },
    "/api/Accounts/DetailsById": {
      "get": {
        "tags": [
          "Accounts"
        ],
        "parameters": [
          {
            "name": "id",
            "in": "query",
            "schema": {
              "type": "integer",
              "format": "int32"
            }
          },
          {
            "name": "accountId",
            "in": "query",
            "schema": {
              "type": "integer",
              "format": "int32"
            }
          }
        ],
        "responses": {
          "200": {
            "description": "Success"
          }
        }
      }
    },
    "/api/Accounts/Register": {
      "post": {
        "tags": [
          "Accounts"
        ],
        "requestBody": {
          "content": {
            "application/json": {
              "schema": {
                "$ref": "#/components/schemas/RegistrationRequest"
              }
            },
            "text/json": {
              "schema": {
                "$ref": "#/components/schemas/RegistrationRequest"
              }
            },
            "application/*+json": {
              "schema": {
                "$ref": "#/components/schemas/RegistrationRequest"
              }
            }
          }
        },
        "responses": {
          "200": {
            "description": "Success"
          }
        }
      }
    },
    "/api/Accounts/List": {
      "post": {
        "tags": [
          "Accounts"
        ],
        "requestBody": {
          "content": {
            "application/json": {
              "schema": {
                "$ref": "#/components/schemas/AccountListRequest"
              }
            },
            "text/json": {
              "schema": {
                "$ref": "#/components/schemas/AccountListRequest"
              }
            },
            "application/*+json": {
              "schema": {
                "$ref": "#/components/schemas/AccountListRequest"
              }
            }
          }
        },
        "responses": {
          "200": {
            "description": "Success"
          }
        }
      }
    },
    "/api/Accounts/SideBarDetailsById/{id}": {
      "get": {
        "tags": [
          "Accounts"
        ],
        "parameters": [
          {
            "name": "id",
            "in": "path",
            "required": true,
            "schema": {
              "type": "integer",
              "format": "int32"
            }
          }
        ],
        "responses": {
          "200": {
            "description": "Success"
          }
        }
      }
    },
    "/api/Accounts/ProfileDetailsById/{id}": {
      "get": {
        "tags": [
          "Accounts"
        ],
        "parameters": [
          {
            "name": "id",
            "in": "path",
            "required": true,
            "schema": {
              "type": "integer",
              "format": "int32"
            }
          }
        ],
        "responses": {
          "200": {
            "description": "Success"
          }
        }
      }
    },
    "/api/Accounts/DashboardStatsById/{id}": {
      "get": {
        "tags": [
          "Accounts"
        ],
        "parameters": [
          {
            "name": "id",
            "in": "path",
            "required": true,
            "schema": {
              "type": "integer",
              "format": "int32"
            }
          }
        ],
        "responses": {
          "200": {
            "description": "Success"
          }
        }
      }
    },
    "/api/Accounts/PersonalInfo": {
      "put": {
        "tags": [
          "Accounts"
        ],
        "requestBody": {
          "content": {
            "application/json": {
              "schema": {
                "$ref": "#/components/schemas/PersonalInfo"
              }
            },
            "text/json": {
              "schema": {
                "$ref": "#/components/schemas/PersonalInfo"
              }
            },
            "application/*+json": {
              "schema": {
                "$ref": "#/components/schemas/PersonalInfo"
              }
            }
          }
        },
        "responses": {
          "200": {
            "description": "Success"
          }
        }
      }
    },
    "/api/Accounts/BioDetails": {
      "put": {
        "tags": [
          "Accounts"
        ],
        "requestBody": {
          "content": {
            "application/json": {
              "schema": {
                "$ref": "#/components/schemas/BioDetails"
              }
            },
            "text/json": {
              "schema": {
                "$ref": "#/components/schemas/BioDetails"
              }
            },
            "application/*+json": {
              "schema": {
                "$ref": "#/components/schemas/BioDetails"
              }
            }
          }
        },
        "responses": {
          "200": {
            "description": "Success"
          }
        }
      }
    },
    "/api/Accounts/OccupationAndEducationDetails": {
      "put": {
        "tags": [
          "Accounts"
        ],
        "requestBody": {
          "content": {
            "application/json": {
              "schema": {
                "$ref": "#/components/schemas/OccupationAndEducationDetails"
              }
            },
            "text/json": {
              "schema": {
                "$ref": "#/components/schemas/OccupationAndEducationDetails"
              }
            },
            "application/*+json": {
              "schema": {
                "$ref": "#/components/schemas/OccupationAndEducationDetails"
              }
            }
          }
        },
        "responses": {
          "200": {
            "description": "Success"
          }
        }
      }
    },
    "/api/Accounts/FamilyDetails": {
      "put": {
        "tags": [
          "Accounts"
        ],
        "requestBody": {
          "content": {
            "application/json": {
              "schema": {
                "$ref": "#/components/schemas/FamilyDetails"
              }
            },
            "text/json": {
              "schema": {
                "$ref": "#/components/schemas/FamilyDetails"
              }
            },
            "application/*+json": {
              "schema": {
                "$ref": "#/components/schemas/FamilyDetails"
              }
            }
          }
        },
        "responses": {
          "200": {
            "description": "Success"
          }
        }
      }
    },
    "/api/Accounts/CheckProfileStepValue": {
      "get": {
        "tags": [
          "Accounts"
        ],
        "parameters": [
          {
            "name": "id",
            "in": "query",
            "schema": {
              "type": "integer",
              "format": "int32"
            }
          },
          {
            "name": "step",
            "in": "query",
            "schema": {
              "type": "string"
            }
          }
        ],
        "responses": {
          "200": {
            "description": "Success"
          }
        }
      }
    },
    "/api/Files": {
      "post": {
        "tags": [
          "Files"
        ],
        "requestBody": {
          "content": {
            "multipart/form-data": {
              "schema": {
                "type": "object",
                "properties": {
                  "file": {
                    "type": "string",
                    "format": "binary"
                  },
                  "accountId": {
                    "type": "integer",
                    "format": "int32"
                  },
                  "fileType": {
                    "type": "string"
                  }
                }
              },
              "encoding": {
                "file": {
                  "style": "form"
                },
                "accountId": {
                  "style": "form"
                },
                "fileType": {
                  "style": "form"
                }
              }
            }
          }
        },
        "responses": {
          "200": {
            "description": "Success"
          }
        }
      }
    },
    "/api/Files/{id}": {
      "get": {
        "tags": [
          "Files"
        ],
        "parameters": [
          {
            "name": "id",
            "in": "path",
            "required": true,
            "schema": {
              "type": "integer",
              "format": "int32"
            }
          }
        ],
        "responses": {
          "200": {
            "description": "Success"
          }
        }
      },
      "delete": {
        "tags": [
          "Files"
        ],
        "parameters": [
          {
            "name": "id",
            "in": "path",
            "required": true,
            "schema": {
              "type": "integer",
              "format": "int32"
            }
          }
        ],
        "responses": {
          "200": {
            "description": "Success"
          }
        }
      }
    },
    "/api/Files/ByAccount": {
      "get": {
        "tags": [
          "Files"
        ],
        "parameters": [
          {
            "name": "AcccountId",
            "in": "query",
            "schema": {
              "type": "integer",
              "format": "int32"
            }
          }
        ],
        "responses": {
          "200": {
            "description": "Success"
          }
        }
      }
    },
    "/api/Files/ByFileType": {
      "get": {
        "tags": [
          "Files"
        ],
        "parameters": [
          {
            "name": "AcccountId",
            "in": "query",
            "schema": {
              "type": "integer",
              "format": "int32"
            }
          },
          {
            "name": "FileType",
            "in": "query",
            "schema": {
              "type": "string"
            }
          }
        ],
        "responses": {
          "200": {
            "description": "Success"
          }
        }
      }
    },
    "/api/Files/SetAsDefault": {
      "put": {
        "tags": [
          "Files"
        ],
        "parameters": [
          {
            "name": "id",
            "in": "query",
            "schema": {
              "type": "integer",
              "format": "int32"
            }
          },
          {
            "name": "AccountId",
            "in": "query",
            "schema": {
              "type": "integer",
              "format": "int32"
            }
          }
        ],
        "responses": {
          "200": {
            "description": "Success"
          }
        }
      }
    },
    "/api/Filter": {
      "post": {
        "tags": [
          "Filter"
        ],
        "requestBody": {
          "content": {
            "application/json": {
              "schema": {
                "$ref": "#/components/schemas/FilterRequest"
              }
            },
            "text/json": {
              "schema": {
                "$ref": "#/components/schemas/FilterRequest"
              }
            },
            "application/*+json": {
              "schema": {
                "$ref": "#/components/schemas/FilterRequest"
              }
            }
          }
        },
        "responses": {
          "200": {
            "description": "Success"
          }
        }
      }
    },
    "/api/Login": {
      "post": {
        "tags": [
          "Login"
        ],
        "requestBody": {
          "content": {
            "application/json": {
              "schema": {
                "$ref": "#/components/schemas/LoginRequest"
              }
            },
            "text/json": {
              "schema": {
                "$ref": "#/components/schemas/LoginRequest"
              }
            },
            "application/*+json": {
              "schema": {
                "$ref": "#/components/schemas/LoginRequest"
              }
            }
          }
        },
        "responses": {
          "200": {
            "description": "Success"
          }
        }
      }
    },
    "/api/LookUpDetails": {
      "post": {
        "tags": [
          "LookUpDetails"
        ],
        "requestBody": {
          "content": {
            "application/json": {
              "schema": {
                "$ref": "#/components/schemas/LookUpDetails"
              }
            },
            "text/json": {
              "schema": {
                "$ref": "#/components/schemas/LookUpDetails"
              }
            },
            "application/*+json": {
              "schema": {
                "$ref": "#/components/schemas/LookUpDetails"
              }
            }
          }
        },
        "responses": {
          "200": {
            "description": "Success"
          }
        }
      },
      "get": {
        "tags": [
          "LookUpDetails"
        ],
        "responses": {
          "200": {
            "description": "Success"
          }
        }
      }
    },
    "/api/LookUpDetails/{id}": {
      "get": {
        "tags": [
          "LookUpDetails"
        ],
        "parameters": [
          {
            "name": "id",
            "in": "path",
            "required": true,
            "schema": {
              "type": "integer",
              "format": "int32"
            }
          }
        ],
        "responses": {
          "200": {
            "description": "Success"
          }
        }
      },
      "put": {
        "tags": [
          "LookUpDetails"
        ],
        "parameters": [
          {
            "name": "id",
            "in": "path",
            "required": true,
            "schema": {
              "type": "integer",
              "format": "int32"
            }
          }
        ],
        "requestBody": {
          "content": {
            "application/json": {
              "schema": {
                "$ref": "#/components/schemas/LookUpDetails"
              }
            },
            "text/json": {
              "schema": {
                "$ref": "#/components/schemas/LookUpDetails"
              }
            },
            "application/*+json": {
              "schema": {
                "$ref": "#/components/schemas/LookUpDetails"
              }
            }
          }
        },
        "responses": {
          "200": {
            "description": "Success"
          }
        }
      },
      "delete": {
        "tags": [
          "LookUpDetails"
        ],
        "parameters": [
          {
            "name": "id",
            "in": "path",
            "required": true,
            "schema": {
              "type": "integer",
              "format": "int32"
            }
          }
        ],
        "responses": {
          "200": {
            "description": "Success"
          }
        }
      }
    },
    "/api/LookUpDetails/ByParentId": {
      "get": {
        "tags": [
          "LookUpDetails"
        ],
        "parameters": [
          {
            "name": "ParentId",
            "in": "query",
            "schema": {
              "type": "integer",
              "format": "int32"
            }
          }
        ],
        "responses": {
          "200": {
            "description": "Success"
          }
        }
      }
    },
    "/api/LookUpDetails/ByMasterName": {
      "get": {
        "tags": [
          "LookUpDetails"
        ],
        "parameters": [
          {
            "name": "name",
            "in": "query",
            "schema": {
              "type": "string"
            }
          }
        ],
        "responses": {
          "200": {
            "description": "Success"
          }
        }
      }
    },
    "/api/Proposal/Send": {
      "post": {
        "tags": [
          "Proposal"
        ],
        "requestBody": {
          "content": {
            "application/json": {
              "schema": {
                "$ref": "#/components/schemas/ProposalRequest"
              }
            },
            "text/json": {
              "schema": {
                "$ref": "#/components/schemas/ProposalRequest"
              }
            },
            "application/*+json": {
              "schema": {
                "$ref": "#/components/schemas/ProposalRequest"
              }
            }
          }
        },
        "responses": {
          "200": {
            "description": "Success"
          }
        }
      }
    }
  },
  "components": {
    "schemas": {
      "AccountListRequest": {
        "type": "object",
        "properties": {
          "filter": {
            "type": "string",
            "nullable": true
          },
          "skip": {
            "type": "integer",
            "format": "int32"
          },
          "take": {
            "type": "integer",
            "format": "int32"
          },
          "accountId": {
            "type": "integer",
            "format": "int32"
          }
        },
        "additionalProperties": false
      },
      "Accounts": {
        "type": "object",
        "properties": {
          "id": {
            "type": "integer",
            "format": "int32"
          },
          "firstName": {
            "type": "string",
            "nullable": true
          },
          "middleName": {
            "type": "string",
            "nullable": true
          },
          "lastName": {
            "type": "string",
            "nullable": true
          },
          "age": {
            "type": "integer",
            "format": "int32",
            "nullable": true
          },
          "gender": {
            "type": "integer",
            "format": "int32",
            "nullable": true
          },
          "religion": {
            "type": "integer",
            "format": "int32",
            "nullable": true
          },
          "email": {
            "type": "string",
            "nullable": true
          },
          "mobileNo": {
            "type": "string",
            "nullable": true
          },
          "password": {
            "type": "string",
            "nullable": true
          },
          "address": {
            "type": "string",
            "nullable": true
          },
          "city": {
            "type": "string",
            "nullable": true
          },
          "district": {
            "type": "integer",
            "format": "int32",
            "nullable": true
          },
          "state": {
            "type": "integer",
            "format": "int32",
            "nullable": true
          },
          "zip": {
            "type": "string",
            "nullable": true
          },
          "country": {
            "type": "integer",
            "format": "int32",
            "nullable": true
          },
          "community": {
            "type": "integer",
            "format": "int32",
            "nullable": true
          },
          "subCommunity": {
            "type": "integer",
            "format": "int32",
            "nullable": true
          },
          "motherTongue": {
            "type": "integer",
            "format": "int32",
            "nullable": true
          },
          "matritalStatus": {
            "type": "integer",
            "format": "int32",
            "nullable": true
          },
          "livingSituation": {
            "type": "integer",
            "format": "int32",
            "nullable": true
          },
          "diet": {
            "type": "integer",
            "format": "int32",
            "nullable": true
          },
          "height": {
            "type": "number",
            "format": "double",
            "nullable": true
          },
          "bodyType": {
            "type": "integer",
            "format": "int32",
            "nullable": true
          },
          "complexion": {
            "type": "integer",
            "format": "int32",
            "nullable": true
          },
          "alcoholDrinker": {
            "type": "boolean",
            "nullable": true
          },
          "smoker": {
            "type": "boolean",
            "nullable": true
          },
          "bio": {
            "type": "string",
            "nullable": true
          },
          "partnerBio": {
            "type": "string",
            "nullable": true
          },
          "highestQualification": {
            "type": "integer",
            "format": "int32",
            "nullable": true
          },
          "profession": {
            "type": "integer",
            "format": "int32",
            "nullable": true
          },
          "annualIncome": {
            "type": "integer",
            "format": "int32",
            "nullable": true
          },
          "fatherName": {
            "type": "string",
            "nullable": true
          },
          "fatherStatus": {
            "type": "integer",
            "format": "int32",
            "nullable": true
          },
          "fatherMobileNo": {
            "type": "string",
            "nullable": true
          },
          "motherName": {
            "type": "string",
            "nullable": true
          },
          "motherStatus": {
            "type": "integer",
            "format": "int32",
            "nullable": true
          },
          "motherMobileNo": {
            "type": "string",
            "nullable": true
          },
          "gurdianName": {
            "type": "string",
            "nullable": true
          },
          "gurdianMobileNo": {
            "type": "string",
            "nullable": true
          },
          "noOfBrothers": {
            "type": "integer",
            "format": "int32",
            "nullable": true
          },
          "noOfMarriedBrothers": {
            "type": "integer",
            "format": "int32",
            "nullable": true
          },
          "noOfSisters": {
            "type": "integer",
            "format": "int32",
            "nullable": true
          },
          "noOfMarriedSisters": {
            "type": "integer",
            "format": "int32",
            "nullable": true
          },
          "familyType": {
            "type": "integer",
            "format": "int32",
            "nullable": true
          },
          "familyReligiousValues": {
            "type": "integer",
            "format": "int32",
            "nullable": true
          },
          "createdOn": {
            "type": "string",
            "format": "date-time",
            "nullable": true
          },
          "updatedOn": {
            "type": "string",
            "format": "date-time",
            "nullable": true
          },
          "isActive": {
            "type": "boolean",
            "nullable": true
          }
        },
        "additionalProperties": false
      },
      "BioDetails": {
        "type": "object",
        "properties": {
          "id": {
            "type": "integer",
            "format": "int32"
          },
          "bio": {
            "type": "string",
            "nullable": true
          },
          "partnerBio": {
            "type": "string",
            "nullable": true
          },
          "updatedOn": {
            "type": "string",
            "format": "date-time",
            "nullable": true
          }
        },
        "additionalProperties": false
      },
      "FamilyDetails": {
        "type": "object",
        "properties": {
          "id": {
            "type": "integer",
            "format": "int32"
          },
          "fatherName": {
            "type": "string",
            "nullable": true
          },
          "fatherStatus": {
            "type": "integer",
            "format": "int32",
            "nullable": true
          },
          "fatherMobileNo": {
            "type": "string",
            "nullable": true
          },
          "motherName": {
            "type": "string",
            "nullable": true
          },
          "motherStatus": {
            "type": "integer",
            "format": "int32",
            "nullable": true
          },
          "motherMobileNo": {
            "type": "string",
            "nullable": true
          },
          "gurdianName": {
            "type": "string",
            "nullable": true
          },
          "gurdianMobileNo": {
            "type": "string",
            "nullable": true
          },
          "noOfBrothers": {
            "type": "integer",
            "format": "int32",
            "nullable": true
          },
          "noOfMarriedBrothers": {
            "type": "integer",
            "format": "int32",
            "nullable": true
          },
          "noOfSisters": {
            "type": "integer",
            "format": "int32",
            "nullable": true
          },
          "noOfMarriedSisters": {
            "type": "integer",
            "format": "int32",
            "nullable": true
          },
          "familyType": {
            "type": "integer",
            "format": "int32",
            "nullable": true
          },
          "familyReligiousValues": {
            "type": "integer",
            "format": "int32",
            "nullable": true
          },
          "updatedOn": {
            "type": "string",
            "format": "date-time",
            "nullable": true
          }
        },
        "additionalProperties": false
      },
      "FilterRequest": {
        "type": "object",
        "properties": {
          "searchText": {
            "type": "string",
            "nullable": true
          }
        },
        "additionalProperties": false
      },
      "LoginRequest": {
        "type": "object",
        "properties": {
          "username": {
            "type": "string",
            "nullable": true
          },
          "password": {
            "type": "string",
            "nullable": true
          }
        },
        "additionalProperties": false
      },
      "LookUpDetails": {
        "type": "object",
        "properties": {
          "id": {
            "type": "integer",
            "format": "int32"
          },
          "lookUpMasterId": {
            "type": "integer",
            "format": "int32"
          },
          "parentId": {
            "type": "integer",
            "format": "int32",
            "nullable": true
          },
          "name": {
            "type": "string",
            "nullable": true
          },
          "displayName": {
            "type": "string",
            "nullable": true
          },
          "createdOn": {
            "type": "string",
            "format": "date-time",
            "nullable": true
          },
          "updatedOn": {
            "type": "string",
            "format": "date-time",
            "nullable": true
          },
          "isActive": {
            "type": "boolean"
          }
        },
        "additionalProperties": false
      },
      "OccupationAndEducationDetails": {
        "type": "object",
        "properties": {
          "id": {
            "type": "integer",
            "format": "int32"
          },
          "highestQualification": {
            "type": "integer",
            "format": "int32",
            "nullable": true
          },
          "passoutYear": {
            "type": "integer",
            "format": "int32",
            "nullable": true
          },
          "profession": {
            "type": "integer",
            "format": "int32",
            "nullable": true
          },
          "annualIncome": {
            "type": "integer",
            "format": "int32",
            "nullable": true
          },
          "updatedOn": {
            "type": "string",
            "format": "date-time",
            "nullable": true
          }
        },
        "additionalProperties": false
      },
      "PersonalInfo": {
        "type": "object",
        "properties": {
          "id": {
            "type": "integer",
            "format": "int32"
          },
          "firstName": {
            "type": "string",
            "nullable": true
          },
          "middleName": {
            "type": "string",
            "nullable": true
          },
          "lastName": {
            "type": "string",
            "nullable": true
          },
          "age": {
            "type": "integer",
            "format": "int32",
            "nullable": true
          },
          "gender": {
            "type": "integer",
            "format": "int32",
            "nullable": true
          },
          "religion": {
            "type": "integer",
            "format": "int32",
            "nullable": true
          },
          "email": {
            "type": "string",
            "nullable": true
          },
          "mobileNo": {
            "type": "string",
            "nullable": true
          },
          "address": {
            "type": "string",
            "nullable": true
          },
          "city": {
            "type": "string",
            "nullable": true
          },
          "district": {
            "type": "integer",
            "format": "int32",
            "nullable": true
          },
          "state": {
            "type": "integer",
            "format": "int32",
            "nullable": true
          },
          "zip": {
            "type": "string",
            "nullable": true
          },
          "country": {
            "type": "integer",
            "format": "int32",
            "nullable": true
          },
          "community": {
            "type": "integer",
            "format": "int32",
            "nullable": true
          },
          "subCommunity": {
            "type": "integer",
            "format": "int32",
            "nullable": true
          },
          "motherTongue": {
            "type": "integer",
            "format": "int32",
            "nullable": true
          },
          "matritalStatus": {
            "type": "integer",
            "format": "int32",
            "nullable": true
          },
          "livingSituation": {
            "type": "integer",
            "format": "int32",
            "nullable": true
          },
          "diet": {
            "type": "integer",
            "format": "int32",
            "nullable": true
          },
          "height": {
            "type": "number",
            "format": "double",
            "nullable": true
          },
          "bodyType": {
            "type": "integer",
            "format": "int32",
            "nullable": true
          },
          "complexion": {
            "type": "integer",
            "format": "int32",
            "nullable": true
          },
          "alcoholDrinker": {
            "type": "boolean",
            "nullable": true
          },
          "smoker": {
            "type": "boolean",
            "nullable": true
          },
          "updatedOn": {
            "type": "string",
            "format": "date-time",
            "nullable": true
          }
        },
        "additionalProperties": false
      },
      "ProposalRequest": {
        "type": "object",
        "properties": {
          "sendTo": {
            "type": "integer",
            "format": "int32"
          },
          "sendBy": {
            "type": "integer",
            "format": "int32"
          }
        },
        "additionalProperties": false
      },
      "RegistrationRequest": {
        "type": "object",
        "properties": {
          "id": {
            "type": "integer",
            "format": "int32"
          },
          "username": {
            "type": "string",
            "nullable": true
          },
          "password": {
            "type": "string",
            "nullable": true
          }
        },
        "additionalProperties": false
      }
    },
    "securitySchemes": {
      "Bearer": {
        "type": "http",
        "description": "Enter 'Bearer' followed by a space and your token. Example: Bearer abc123",
        "scheme": "Bearer",
        "bearerFormat": "JWT"
      }
    }
  },
  "security": [
    {
      "Bearer": [ ]
    }
  ]
}